[{"userName":"q","fullName":"sale s","age":7,"favoriteGenres":null,"password":"322c9d7146bfdee8386672d224211874","friends":null,"artistList":null,"albumList":null,"songList":null,"playlist":null},{"userName":"gtg","fullName":"jgj jgj","age":4,"favoriteGenres":null,"password":"a16bd41efaf1a9e5168e5bfe7aed3671","friends":null,"artistList":null,"albumList":null,"songList":null,"playlist":null},{"userName":"Steve","fullName":"Carlos  Alvarao","age":21,"favoriteGenres":null,"password":"403de972a0a9af21a25f9ce85766c459","friends":null,"artistList":null,"albumList":null,"songList":null,"playlist":null},{"userName":"Stevealv121","fullName":"Steve Alvarado","age":21,"favoriteGenres":null,"password":"hola","friends":null,"artistList":null,"albumList":null,"songList":null,"playlist":null},{"userName":"Stevealv121","fullName":"Steve Alvarado","age":21,"favoriteGenres":null,"password":"hola","friends":null,"artistList":null,"albumList":null,"songList":null,"playlist":null},{"userName":"Stevealv121","fullName":"Steve Alvarado","age":21,"favoriteGenres":null,"password":"hola","friends":null,"artistList":null,"albumList":null,"songList":null,"playlist":null}]